Metadata-Version: 1.0
Name: rpa-olymp
Version: 0.0
Summary: Description bib
Home-page: UNKNOWN
Author: UNKNOWN
Author-email: dima.prytkov.dima@mail.ru
License: UNKNOWN
Platform: UNKNOWN
